{"original_game":{"id":"1d55404e-8973-4596-b96a-4571cd61004a","rounds":2,"defenderUnitCount":1,"spawn":1,"targets":[2,3,4,5,6],"graphConfig":{"vertexCount":12,"isDirected":false,"edges":[{"from":0,"to":7},{"from":3,"to":8},{"from":1,"to":2},{"from":0,"to":4},{"from":0,"to":10},{"from":2,"to":7},{"from":6,"to":11},{"from":1,"to":11},{"from":1,"to":4},{"from":6,"to":10},{"from":0,"to":5},{"from":5,"to":9},{"from":0,"to":8},{"from":1,"to":3},{"from":1,"to":9}]},"targetAttackerRewards":[0.36,0.21,0.55,0.61,0.8],"targetDefenderPenalties":[-0.14,-0.87,-0.18,-0.22,-0.91],"vertexAttackerPenalties":[-0.31,-0.38,-0.66,-0.19,-0.46,-0.25,-1.0,-0.13,-0.59,-0.2,-0.46,-0.48],"vertexDefenderRewards":[0.0,0.0,0.0,0.0,0.0,0.0,0.0,0.0,0.0,0.0,0.0,0.0]},"scenarios":[{"id":"simple-2step-5targets-4.ggame_scen_1","game_id":"1d55404e-8973-4596-b96a-4571cd61004a","filename":"simple-2step-5targets-4.ggame","defender_strategy":[{"prob":0.1791579468332587,"path":[0,7,2]},{"prob":0.25871726829313857,"path":[0,8,3]},{"prob":0.13066918244228454,"path":[0,4,4]},{"prob":0.2907541203294164,"path":[0,5,5]},{"prob":0.14070148210190175,"path":[0,10,6]}],"solutions":{"Rational":{"path":[1,11,6],"eu_rational":0.5467373322165769},"PT":{"path":[1,2,2],"eu_subjective":0.5234763101044763,"eu_rational":0.36}}},{"id":"simple-2step-5targets-4.ggame_scen_2","game_id":"1d55404e-8973-4596-b96a-4571cd61004a","filename":"simple-2step-5targets-4.ggame","defender_strategy":[{"prob":0.4245190345461038,"path":[0,7,2]},{"prob":0.14013674375474014,"path":[0,8,3]},{"prob":0.10406714618000226,"path":[0,4,4]},{"prob":0.17379252909233295,"path":[0,5,5]},{"prob":0.15748454642682075,"path":[0,10,6]}],"solutions":{"Rational":{"path":[1,11,6],"eu_rational":0.5165278164317226},"PT":{"path":[1,2,2],"eu_subjective":0.5148278671615185,"eu_rational":0.35999999999999993}}},{"id":"simple-2step-5targets-4.ggame_scen_3","game_id":"1d55404e-8973-4596-b96a-4571cd61004a","filename":"simple-2step-5targets-4.ggame","defender_strategy":[{"prob":0.2541852000065231,"path":[0,7,2]},{"prob":0.1305617379245446,"path":[0,8,3]},{"prob":0.10419523272514893,"path":[0,4,4]},{"prob":0.2411602148004021,"path":[0,5,5]},{"prob":0.2698976145433813,"path":[0,10,6]}],"solutions":{"Rational":{"path":[1,1,4],"eu_rational":0.4447628149475996},"PT":{"path":[1,2,2],"eu_subjective":0.5212389640642976,"eu_rational":0.36}}},{"id":"simple-2step-5targets-4.ggame_scen_4","game_id":"1d55404e-8973-4596-b96a-4571cd61004a","filename":"simple-2step-5targets-4.ggame","defender_strategy":[{"prob":0.2706037076433085,"path":[0,7,2]},{"prob":0.2016186060166301,"path":[0,8,3]},{"prob":0.14028604085380852,"path":[0,4,4]},{"prob":0.19229039926269434,"path":[0,5,5]},{"prob":0.1952012462235586,"path":[0,10,6]}],"solutions":{"Rational":{"path":[1,11,6],"eu_rational":0.44863775679759466},"PT":{"path":[1,2,2],"eu_subjective":0.5270946504749565,"eu_rational":0.36}}},{"id":"simple-2step-5targets-4.ggame_scen_5","game_id":"1d55404e-8973-4596-b96a-4571cd61004a","filename":"simple-2step-5targets-4.ggame","defender_strategy":[{"prob":0.238934842370236,"path":[0,7,2]},{"prob":0.3166499508795098,"path":[0,8,3]},{"prob":0.23486248743439453,"path":[0,4,4]},{"prob":0.07330199165099505,"path":[0,5,5]},{"prob":0.13625072766486465,"path":[0,10,6]}],"solutions":{"Rational":{"path":[1,11,6],"eu_rational":0.5547486902032436},"PT":{"path":[1,9,5],"eu_subjective":0.6199945883955976,"eu_rational":0.5469602871801443}}},{"id":"simple-2step-5targets-4.ggame_scen_6","game_id":"1d55404e-8973-4596-b96a-4571cd61004a","filename":"simple-2step-5targets-4.ggame","defender_strategy":[{"prob":0.030836617104827543,"path":[0,7,2]},{"prob":0.04652957009006064,"path":[0,8,3]},{"prob":0.15622896876307504,"path":[0,4,4]},{"prob":0.36169841506760314,"path":[0,5,5]},{"prob":0.40470642897443354,"path":[0,10,6]}],"solutions":{"Rational":{"path":[1,1,4],"eu_rational":0.3922087415492942},"PT":{"path":[1,2,2],"eu_subjective":0.48132504627313843,"eu_rational":0.36}}},{"id":"simple-2step-5targets-4.ggame_scen_7","game_id":"1d55404e-8973-4596-b96a-4571cd61004a","filename":"simple-2step-5targets-4.ggame","defender_strategy":[{"prob":0.16282200106174582,"path":[0,7,2]},{"prob":0.1793130413303104,"path":[0,8,3]},{"prob":0.23364237881827588,"path":[0,4,4]},{"prob":0.1865733419124257,"path":[0,5,5]},{"prob":0.23764923687724213,"path":[0,10,6]}],"solutions":{"Rational":{"path":[1,9,5],"eu_rational":0.44954692595531387},"PT":{"path":[1,2,2],"eu_subjective":0.5283477513697342,"eu_rational":0.36}}},{"id":"simple-2step-5targets-4.ggame_scen_8","game_id":"1d55404e-8973-4596-b96a-4571cd61004a","filename":"simple-2step-5targets-4.ggame","defender_strategy":[{"prob":0.2368637432186504,"path":[0,7,2]},{"prob":0.16905536017678502,"path":[0,8,3]},{"prob":0.3582345608773702,"path":[0,4,4]},{"prob":0.13376688103272383,"path":[0,5,5]},{"prob":0.10207945469447056,"path":[0,10,6]}],"solutions":{"Rational":{"path":[1,11,6],"eu_rational":0.616256981549953},"PT":{"path":[1,9,5],"eu_subjective":0.5473723119745346,"eu_rational":0.4949604823118576}}},{"id":"simple-2step-5targets-4.ggame_scen_9","game_id":"1d55404e-8973-4596-b96a-4571cd61004a","filename":"simple-2step-5targets-4.ggame","defender_strategy":[{"prob":0.07684217679103113,"path":[0,7,2]},{"prob":0.2078956125045377,"path":[0,8,3]},{"prob":0.28155397955605843,"path":[0,4,4]},{"prob":0.18168239988173748,"path":[0,5,5]},{"prob":0.2520258312666353,"path":[0,10,6]}],"solutions":{"Rational":{"path":[1,9,5],"eu_rational":0.45375313610170576},"PT":{"path":[1,2,2],"eu_subjective":0.5194646176919798,"eu_rational":0.36}}},{"id":"simple-2step-5targets-4.ggame_scen_10","game_id":"1d55404e-8973-4596-b96a-4571cd61004a","filename":"simple-2step-5targets-4.ggame","defender_strategy":[{"prob":0.1924363285366494,"path":[0,7,2]},{"prob":0.11137393928020273,"path":[0,8,3]},{"prob":0.24677927177457384,"path":[0,4,4]},{"prob":0.24486500297825964,"path":[0,5,5]},{"prob":0.20454545743031444,"path":[0,10,6]}],"solutions":{"Rational":{"path":[1,11,6],"eu_rational":0.43181817662543415},"PT":{"path":[1,2,2],"eu_subjective":0.5251814876040609,"eu_rational":0.36}}}]}